{
    "LC01": {
      "full": {
        "title": "Tour trải nghiệm trọn vẹn làng chè Tân Cương",
        "weatherSuggestion": ["sunny", "cool"],
        "steps": [
          {
            "title": "Khám phá văn hóa trà Tân Cương",
            "where": "Không gian văn hóa Trà Tân Cương (Bảo tàng trà Thái Nguyên) – Xóm Soi Vàng, xã Tân Cương, TP. Thái Nguyên (GPS: 21.5621, 105.7483)",
            "what": "Tham quan khu trưng bày hiện vật về lịch sử và quy trình sản xuất trà; tìm hiểu câu chuyện vùng chè Tân Cương; thưởng trà miễn phí tại khu trải nghiệm.",
            "durationMin": 45
          },
          {
            "title": "Check-in đồi chè Tân Cương",
            "where": "Khu đồi chè Tân Cương – các xóm Soi Vàng, Khuôn Nam, Hồng Thái (xã Tân Cương, TP. Thái Nguyên)",
            "what": "Tản bộ giữa các luống chè xanh; chụp ảnh toàn cảnh đồi chè; trải nghiệm không khí vùng chè và giao lưu với người dân địa phương.",
            "durationMin": 35
          },
          {
            "title": "Trải nghiệm hái chè và xem quy trình làm trà",
            "where": "HTX Chè Hảo Đạt – Đường Tân Cương, xã Tân Cương, TP. Thái Nguyên (GPS: 21.5542, 105.7485)",
            "what": "Học cách chọn và hái búp chè đúng kỹ thuật; tham quan khu sản xuất; quan sát quy trình sao, vò và sấy trà; tìm hiểu tiêu chuẩn chất lượng trà Tân Cương.",
            "durationMin": 70
          },
          {
            "title": "Thưởng trà và học pha trà truyền thống",
            "where": "HTX Tâm Trà Việt – Cơ sở 3, Xóm Nam Thái, xã Tân Cương, TP. Thái Nguyên",
            "what": "Thưởng thức trà Tân Cương chuẩn vị; học cách tráng ấm, pha trà và cảm nhận hương vị; giao lưu với người làm trà hoặc nghệ nhân địa phương.",
            "durationMin": 45
          },
          {
            "title": "Mua trà đặc sản và quà lưu niệm",
            "where": "Các điểm bán trà uy tín tại xã Tân Cương (HTX Chè Hảo Đạt, HTX Chè Trung Du Tân Cương – An Dương Trà, HTX Chè Phúc Linh, HTX Chè Thủy Thuật)",
            "what": "Lựa chọn các loại trà đặc sản như trà móc câu, trà đinh hoặc trà ướp hương; tìm hiểu cách phân biệt trà ngon; mua quà biếu và đóng gói mang về.",
            "durationMin": 30
          }
        ]
      }
    }
  }